cuefig/__init__.py
cuefig/logger/__init__.py
cuefig/logger/logging.yaml
cuefig/utils/__init__.py
cuefig-0.0.2.dist-info/LICENSE
cuefig-0.0.2.dist-info/METADATA
cuefig-0.0.2.dist-info/WHEEL
cuefig-0.0.2.dist-info/top_level.txt
cuefig-0.0.2.dist-info/RECORD
